odoo/addons/product_category_active/README.rst
odoo/addons/product_category_active/__init__.py
odoo/addons/product_category_active/__manifest__.py
odoo/addons/product_category_active/i18n/ca.po
odoo/addons/product_category_active/i18n/de.po
odoo/addons/product_category_active/i18n/es.po
odoo/addons/product_category_active/i18n/it.po
odoo/addons/product_category_active/i18n/product_category_active.pot
odoo/addons/product_category_active/i18n/pt.po
odoo/addons/product_category_active/models/__init__.py
odoo/addons/product_category_active/models/product_category.py
odoo/addons/product_category_active/readme/CONTRIBUTORS.rst
odoo/addons/product_category_active/readme/DESCRIPTION.rst
odoo/addons/product_category_active/readme/ROADMAP.rst
odoo/addons/product_category_active/readme/USAGE.rst
odoo/addons/product_category_active/static/description/icon.png
odoo/addons/product_category_active/static/description/index.html
odoo/addons/product_category_active/tests/__init__.py
odoo/addons/product_category_active/tests/test_product_category_active.py
odoo/addons/product_category_active/views/product_views.xml
odoo14_addon_product_category_active-14.0.1.0.1.dev9.dist-info/METADATA
odoo14_addon_product_category_active-14.0.1.0.1.dev9.dist-info/WHEEL
odoo14_addon_product_category_active-14.0.1.0.1.dev9.dist-info/top_level.txt
odoo14_addon_product_category_active-14.0.1.0.1.dev9.dist-info/RECORD
